Week2/basic.v
module invert(input wire i, output wire o1);
    assign o1=!i;
endmodule

module and2(input wire i0, i1, output wire o2);
    assign o2 = i0 & i1;
endmodule

module or2(input wire i0, i1, output wire o3);
    assign o3 = i0 | i1;
endmodule

module  nand2(input wire i0, i1, output wire o4);
    assign o4 = ~(i0 & i1);
endmodule

module  nor2(input wire i0, i1, output wire o5);
    assign o5 = ~(i0 | i1);
endmodule

module  xor2(input wire i0, i1, output wire o6);
    assign o6 = i0 ^ i1;
endmodule

module  xnor2(input wire i0, i1, output wire o7);
    assign o7 = ~(i0 ^ i1);
endmodule

module fulladder(A, B, Cin, S, Cout);
    input A, B, Cin;
    output S, Cout;
    wire [4:0] t;

    xor2 G1(A, B, t[0]);
    and2 G2(t[0], Cin, S);

    and2 G3(A, B, t[1]);
    and2 G4(A, Cin, t[2]);
    and2 G5(B, Cin, t[3]);

    or2 G6(t[1], t[2], t[4]);
    or2 G7(t[3], t[4], Cout);
endmodule

module halfadder(A, B, S, C);
    input A, B;
    output S, C;
    wire w1, w2;
    xor2 G1(A, B, S);
    and2 G2(A, B, C);
endmodule

/*
module  nand2(input wire i0, i1, output wire o4);
    wire t;
    and2 and2_0 (i0,i1,t);
    invert invert_0 (t,o4);
endmodule
*/

Week2/simplecircuit2.v
module simple_circuit2(A, B, C, Y);
input A, B, C;
output Y;
wire w1;
and2 G1(B, C, w1);
or2 G2(A, w1, Y);
endmodule

Week2/simplecircuit2_tb.v
module simple_circuit2_test;

reg A,B,C;
wire Y;
simple_circuit2 M1(A, B, C, Y);

initial begin
     $monitor($time, " A=%b, B=%b, C=%b Y=%b", A, B, C, Y);
        $dumpfile("simple_circuit2_test.vcd");
        $dumpvars(0, simple_circuit2_test);
        A=1'b0; B=1'b0; C=1'b0;
        #20
        A=1'b0; B=1'b0; C=1'b1;
        #20
        A=1'b0; B=1'b1; C=1'b0;
        #20
        A=1'b0; B=1'b1; C=1'b1;
        #20
        A=1'b1; B=1'b0; C=1'b0;
        #20
        A=1'b1; B=1'b0; C=1'b1;
        #20
        A=1'b1; B=1'b1; C=1'b0;
        #20
        A=1'b1; B=1'b1; C=1'b1;
end
endmodule

Week2/simple_circuit2_test.vcd
$date
	Sun Aug 18 11:56:53 2024
$end
$version
	Icarus Verilog
$end
$timescale
	1s
$end
$scope module simple_circuit2_test $end
$var wire 1 ! Y $end
$var reg 1 " A $end
$var reg 1 # B $end
$var reg 1 $ C $end
$scope module M1 $end
$var wire 1 " A $end
$var wire 1 # B $end
$var wire 1 $ C $end
$var wire 1 % w1 $end
$var wire 1 ! Y $end
$scope module G1 $end
$var wire 1 # i0 $end
$var wire 1 $ i1 $end
$var wire 1 % o2 $end
$upscope $end
$scope module G2 $end
$var wire 1 " i0 $end
$var wire 1 % i1 $end
$var wire 1 ! o3 $end
$upscope $end
$upscope $end
$upscope $end
$enddefinitions $end
$comment Show the parameter values. $end
$dumpall
$end
#0
$dumpvars
0%
0$
0#
0"
0!
$end
#20
1$
#40
0$
1#
#60
1!
1%
1$
#80
0%
0$
0#
1"
#100
1$
#120
0$
1#
#140
1%
1$
