Week2/simple_circuit.v
module not1(input wire i, output wire o);
    assign o = ~i;
endmodule

module and2(input wire a, b, output wire o);
    assign o = a&b;
endmodule

module nand2(input wire a, b, output wire o);
    wire t;
    and2 G1(a,b,t);
    not1 G2(t,o);
endmodule

module xor2(input wire a, b, output wire o);
    wire t1, t2, t3;
    nand2 G1(a, b, t1);
    nand2 G2(a, t1, t2);
    nand2 G3(b, t1, t3);
    nand2 G4(t2, t3, o);
endmodule

module simple_circuit(input wire a, b, c, output wire o);
    wire t1, t2;
    xor2 G1(a, b, t1);
    xor2 G2(t1, c, t2);
    not1 G3(t2, o);
endmodule

module simple_circuit_tb();
reg a, b, c;
wire o;

simple_circuit M1(a,b,c,o);

initial begin
    $dumpfile("simple_circuit_test.vcd");
    $dumpvars(0, M1);
    $monitor($time, " A=%b, B=%b, C=%b Y=%b", a, b, c, o);

    a=1'b0; b=1'b0; c=1'b0; #20;
    a=1'b0; b=1'b0; c=1'b1; #20;
    a=1'b0; b=1'b1; c=1'b0; #20;
    a=1'b0; b=1'b1; c=1'b1; #20;
    a=1'b1; b=1'b0; c=1'b0; #20;
    a=1'b1; b=1'b0; c=1'b1; #20;
    a=1'b1; b=1'b1; c=1'b0; #20;
    a=1'b1; b=1'b1; c=1'b1; #20;
    $finish;
end
endmodule

Week2/simple_circuit_test.vcd
$date
	Thu Sep 19 10:48:56 2024
$end
$version
	Icarus Verilog
$end
$timescale
	1s
$end
$scope module simple_circuit_tb $end
$scope module M1 $end
$var wire 1 ! a $end
$var wire 1 " b $end
$var wire 1 # c $end
$var wire 1 $ t2 $end
$var wire 1 % t1 $end
$var wire 1 & o $end
$scope module G1 $end
$var wire 1 ! a $end
$var wire 1 " b $end
$var wire 1 ' t3 $end
$var wire 1 ( t2 $end
$var wire 1 ) t1 $end
$var wire 1 % o $end
$scope module G1 $end
$var wire 1 ! a $end
$var wire 1 " b $end
$var wire 1 * t $end
$var wire 1 ) o $end
$scope module G1 $end
$var wire 1 ! a $end
$var wire 1 " b $end
$var wire 1 * o $end
$upscope $end
$scope module G2 $end
$var wire 1 * i $end
$var wire 1 ) o $end
$upscope $end
$upscope $end
$scope module G2 $end
$var wire 1 ! a $end
$var wire 1 ) b $end
$var wire 1 + t $end
$var wire 1 ( o $end
$scope module G1 $end
$var wire 1 ! a $end
$var wire 1 ) b $end
$var wire 1 + o $end
$upscope $end
$scope module G2 $end
$var wire 1 + i $end
$var wire 1 ( o $end
$upscope $end
$upscope $end
$scope module G3 $end
$var wire 1 " a $end
$var wire 1 ) b $end
$var wire 1 , t $end
$var wire 1 ' o $end
$scope module G1 $end
$var wire 1 " a $end
$var wire 1 ) b $end
$var wire 1 , o $end
$upscope $end
$scope module G2 $end
$var wire 1 , i $end
$var wire 1 ' o $end
$upscope $end
$upscope $end
$scope module G4 $end
$var wire 1 ( a $end
$var wire 1 ' b $end
$var wire 1 - t $end
$var wire 1 % o $end
$scope module G1 $end
$var wire 1 ( a $end
$var wire 1 ' b $end
$var wire 1 - o $end
$upscope $end
$scope module G2 $end
$var wire 1 - i $end
$var wire 1 % o $end
$upscope $end
$upscope $end
$upscope $end
$scope module G2 $end
$var wire 1 % a $end
$var wire 1 # b $end
$var wire 1 . t3 $end
$var wire 1 / t2 $end
$var wire 1 0 t1 $end
$var wire 1 $ o $end
$scope module G1 $end
$var wire 1 % a $end
$var wire 1 # b $end
$var wire 1 1 t $end
$var wire 1 0 o $end
$scope module G1 $end
$var wire 1 % a $end
$var wire 1 # b $end
$var wire 1 1 o $end
$upscope $end
$scope module G2 $end
$var wire 1 1 i $end
$var wire 1 0 o $end
$upscope $end
$upscope $end
$scope module G2 $end
$var wire 1 % a $end
$var wire 1 0 b $end
$var wire 1 2 t $end
$var wire 1 / o $end
$scope module G1 $end
$var wire 1 % a $end
$var wire 1 0 b $end
$var wire 1 2 o $end
$upscope $end
$scope module G2 $end
$var wire 1 2 i $end
$var wire 1 / o $end
$upscope $end
$upscope $end
$scope module G3 $end
$var wire 1 # a $end
$var wire 1 0 b $end
$var wire 1 3 t $end
$var wire 1 . o $end
$scope module G1 $end
$var wire 1 # a $end
$var wire 1 0 b $end
$var wire 1 3 o $end
$upscope $end
$scope module G2 $end
$var wire 1 3 i $end
$var wire 1 . o $end
$upscope $end
$upscope $end
$scope module G4 $end
$var wire 1 / a $end
$var wire 1 . b $end
$var wire 1 4 t $end
$var wire 1 $ o $end
$scope module G1 $end
$var wire 1 / a $end
$var wire 1 . b $end
$var wire 1 4 o $end
$upscope $end
$scope module G2 $end
$var wire 1 4 i $end
$var wire 1 $ o $end
$upscope $end
$upscope $end
$upscope $end
$scope module G3 $end
$var wire 1 $ i $end
$var wire 1 & o $end
$upscope $end
$upscope $end
$upscope $end
$enddefinitions $end
$comment Show the parameter values. $end
$dumpall
$end
#0
$dumpvars
14
03
02
01
10
1/
1.
1-
0,
0+
0*
1)
1(
1'
1&
0%
0$
0#
0"
0!
$end
#20
0&
1$
04
0.
13
1#
#40
0/
0&
12
1$
1%
04
0-
1.
0'
03
1,
0#
1"
#60
1&
0$
14
1/
02
00
1.
11
03
1#
#80
0&
1$
04
0/
12
10
1'
0(
01
0,
1+
0#
0"
1!
#100
1&
0$
14
1/
02
00
1.
11
03
1#
#120
1&
0$
0%
14
1-
1/
1(
02
0+
10
0)
1'
01
1*
0,
0#
1"
#140
0&
1$
04
0.
13
1#
