Week3/mux2.v
module mux2(input wire i0, i1, j, output wire o);
 assign o = (j==0)?i0:i1;
endmodule

Week3/mux2_tb.v
module TB;
reg A, B, S;
wire X;
initial begin
    $monitor("At time %0t: S = %b, A = %b, B = %b, X = %b", $time, S, A, B, X);
    $dumpfile("mux2_test.vcd");
    $dumpvars(0, TB);
end

mux2 newmux(.i0(A), .i1(B), .j(S), .o(X));

initial begin
    S=1'b0; A=1'b0; B=1'b0; #5;
    S=1'b0; A=1'b0; B=1'b1; #5;
    S=1'b0; A=1'b1; B=1'b0; #5;
    S=1'b0; A=1'b1; B=1'b1; #5;
    S=1'b1; A=1'b0; B=1'b0; #5;
    S=1'b1; A=1'b0; B=1'b1; #5;
    S=1'b1; A=1'b1; B=1'b0; #5;
    S=1'b1; A=1'b1; B=1'b1; #5;
end
endmodule

Week3/mux2_test.vcd
$date
	Tue Aug 20 16:45:27 2024
$end
$version
	Icarus Verilog
$end
$timescale
	1s
$end
$scope module TB $end
$var wire 1 ! X $end
$var reg 1 " A $end
$var reg 1 # B $end
$var reg 1 $ S $end
$scope module newmux $end
$var wire 1 " i0 $end
$var wire 1 # i1 $end
$var wire 1 $ j $end
$var wire 1 ! o $end
$upscope $end
$upscope $end
$enddefinitions $end
$comment Show the parameter values. $end
$dumpall
$end
#0
$dumpvars
0$
0#
0"
0!
$end
#5
1#
#10
1!
0#
1"
#15
1#
#20
0!
0#
0"
1$
#25
1!
1#
#30
0!
0#
1"
#35
1!
1#
